edc_facility/__init__.py
edc_facility/admin.py
edc_facility/admin_site.py
edc_facility/apps.py
edc_facility/auth_objects.py
edc_facility/auths.py
edc_facility/constants.py
edc_facility/default_definitions.py
edc_facility/exceptions.py
edc_facility/facility.py
edc_facility/holidays.py
edc_facility/holidays_disabled.py
edc_facility/import_holidays.py
edc_facility/list_data.py
edc_facility/model_mixins.py
edc_facility/modeladmin_mixins.py
edc_facility/system_checks.py
edc_facility/urls.py
edc_facility/utils.py
edc_facility/form_validators/__init__.py
edc_facility/form_validators/health_facility_form_validator.py
edc_facility/forms/__init__.py
edc_facility/forms/health_facility_form.py
edc_facility/management/__init__.py
edc_facility/management/commands/__init__.py
edc_facility/management/commands/import_holidays.py
edc_facility/migrations/0001_initial.py
edc_facility/migrations/0002_auto_20180102_1158.py
edc_facility/migrations/0003_auto_20190901_1100.py
edc_facility/migrations/0004_auto_20210423_1451.py
edc_facility/migrations/0005_healthfacility_healthfacilitytypes_and_more.py
edc_facility/migrations/0006_alter_healthfacility_health_facility_type.py
edc_facility/migrations/0007_healthfacilitytypes_extra_value.py
edc_facility/migrations/0008_alter_healthfacility_device_created_and_more.py
edc_facility/migrations/0009_alter_healthfacility_options_and_more.py
edc_facility/migrations/0010_remove_healthfacility_edc_facilit_modifie_dcf8ac_idx_and_more.py
edc_facility/migrations/0011_remove_healthfacilitytypes_edc_facilit_name_78007a_idx.py
edc_facility/migrations/0012_alter_holiday_unique_together_and_more.py
edc_facility/migrations/0013_alter_healthfacility_site_and_more.py
edc_facility/migrations/0014_healthfacility_title_historicalhealthfacility_title.py
edc_facility/migrations/__init__.py
edc_facility/models/__init__.py
edc_facility/models/health_facility.py
edc_facility/models/holiday.py
edc_facility/models/list_models.py
edc_facility/tests/__init__.py
edc_facility-1.0.2.dist-info/AUTHORS
edc_facility-1.0.2.dist-info/LICENSE
edc_facility-1.0.2.dist-info/METADATA
edc_facility-1.0.2.dist-info/WHEEL
edc_facility-1.0.2.dist-info/top_level.txt
edc_facility-1.0.2.dist-info/RECORD
